README.md
setup.py
loleventdata/__init__.py
loleventdata/loleventdata.py
loleventdata.egg-info/PKG-INFO
loleventdata.egg-info/SOURCES.txt
loleventdata.egg-info/dependency_links.txt
loleventdata.egg-info/requires.txt
loleventdata.egg-info/top_level.txt