Metadata-Version: 1.0
Name: loleventdata
Version: 0.2.0
Summary: team data & player data
Home-page: https://github.com/HanQinXuan/lol_data_api
Author: HanQinXuan
Author-email: han981130@gmail.com
License: MIT Licence
Keywords: pip,python,lol,wanplus,api,crawler
Platform: any
